README.rst
__init__.py
example.py
setup.py
simple_watchdog_timer.py
simple_watchdog_timer.egg-info/PKG-INFO
simple_watchdog_timer.egg-info/SOURCES.txt
simple_watchdog_timer.egg-info/dependency_links.txt
simple_watchdog_timer.egg-info/top_level.txt