Metadata-Version: 1.0
Name: simple-watchdog-timer
Version: 0.1.1
Summary: A simple WatchDog Timer (WDT) to trigger events if inactivity, of a time dependent task, occur for a specified amount of time.
Home-page: https://github.com/hjortlund/simple_watchdog_timer
Author: Christoffer Hjortlund
Author-email: hjortlund@gmail.com
License: MIT
Platform: UNKNOWN
